[
    {
        "address": "address1",
        "zip": "zip1",
        "mobile": "mobile1",
        "home": "home1",
        "email": "email1",
        "city": "city1",
        "state": "state1",
        "name": "person1"
    },
    {
        "address": "address2",
        "zip": "zip2",
        "mobile": "mobile2",
        "home": "home2",
        "email": "email2",
        "city": "city2",
        "state": "state2",
        "name": "person2"
    },
    {
        "address": "address3",
        "zip": "zip3",
        "mobile": "mobile3",
        "home": "home3",
        "email": "email3",
        "city": "city3",
        "state": "state3",
        "name": "person3"
    }
]
